Adderfsm.v
module adder(
    input clk,rst,a,b,
    output reg stream
);
    
//State Encoding

parameter C0 = 1'b0,C1 = 1'b1;

reg present_state,next_state;

//Present State Logic

always @(posedge clk or posedge rst) begin
    if (rst) begin
        present_state <= C0;
        //stream <= 0;
    end else begin
        present_state <= next_state;
    end
end

//Next State Logic

always @(*) begin
    case (present_state)
        C0 : begin
            stream = a ^ b ^ present_state;
            if (a & b) begin
                next_state = C1;
            end else begin
                next_state = C0;
            end
            end
        C1 : begin
            stream = a ^ b ^ present_state;
            if (~(a | b)) begin
                next_state = C0;
            end else begin
                next_state = C1;
            end
            end
        default : begin
            next_state = C0;
            stream = 0;
        end
    endcase
end


endmodule

Testbench.v
`include "Adderfsm.v"
`timescale 1ns/1ns

module test;

	reg clk,a,b,rst;
	wire stream;
	
	adder dut
	(
		.clk(clk),
		.rst(rst),
		.a(a),
        .b(b),
        .stream(stream)
	);
	
	initial
    begin
      clk = 0;
      forever #5 clk = ~clk;
    end
	
	initial
	begin
		rst = 0;
		a = 1'b0; b = 1'b0;

		// #10 rst = 0;
        // #10 a = 0; b= 0;
		// #10 a = 0; b= 1;
		// #10 a = 1; b= 1;
		// #10 a = 1; b= 1;
		// #10 a = 0; b= 1;
		// #10 a = 1; b= 0;
		// #10 a = 0; b= 0;

		repeat(100) begin
			#10
			a = $random % 2;
			b = $random % 2;
		end
		
	end

initial begin
  $monitor($time, " a = %0b , b = %0b , stream = %0b" , a,b,stream);
end
	
initial begin
	$dumpfile("fsm.vcd");
	$dumpvars(0,test);

	#2000 $finish;
end
endmodule

fsm.vcd
$date
	Fri May 16 04:17:16 2025
$end
$version
	Icarus Verilog
$end
$timescale
	1ns
$end
$scope module test $end
$var wire 1 ! stream $end
$var reg 1 " a $end
$var reg 1 # b $end
$var reg 1 $ clk $end
$var reg 1 % rst $end
$scope module dut $end
$var wire 1 " a $end
$var wire 1 # b $end
$var wire 1 $ clk $end
$var wire 1 % rst $end
$var parameter 1 & C0 $end
$var parameter 1 ' C1 $end
$var reg 1 ( next_state $end
$var reg 1 ) present_state $end
$var reg 1 ! stream $end
$upscope $end
$upscope $end
$enddefinitions $end
$comment Show the parameter values. $end
$dumpall
1'
0&
$end
#0
$dumpvars
x)
0(
0%
0$
0#
0"
0!
$end
#5
0)
1$
#10
1!
0$
1#
#15
1$
#20
1(
0!
0$
1"
#25
1!
1)
1$
#30
0$
#35
1$
#40
0!
0$
0#
#45
1$
#50
1!
0$
1#
#55
1$
#60
0!
0$
0"
#65
1$
#70
0$
0#
1"
#75
1$
#80
0$
#85
1$
#90
0$
#95
1$
#100
1!
0$
1#
#105
1$
#110
0!
0$
0"
#115
1$
#120
0(
1!
0$
0#
#125
0!
0)
1$
#130
1!
0$
1#
#135
1$
#140
0$
#145
1$
#150
1(
0!
0$
1"
#155
1!
1)
1$
#160
0!
0$
0#
#165
1$
#170
0(
1!
0$
0"
#175
0!
0)
1$
#180
1!
0$
1#
#185
1$
#190
0$
#195
1$
#200
1(
0!
0$
1"
#205
1!
1)
1$
#210
0$
#215
1$
#220
0(
0$
0#
0"
#225
0!
0)
1$
#230
1(
0$
1#
1"
#235
1!
1)
1$
#240
0!
0$
0#
#245
1$
#250
0(
1!
0$
0"
#255
0!
0)
1$
#260
0$
#265
1$
#270
1!
0$
1"
#275
1$
#280
0$
1#
0"
#285
1$
#290
0$
0#
1"
#295
1$
#300
0!
0$
0"
#305
1$
#310
0$
#315
1$
#320
1(
0$
1#
1"
#325
1!
1)
1$
#330
0$
#335
1$
#340
0!
0$
0#
#345
1$
#350
0$
1#
0"
#355
1$
#360
1!
0$
1"
#365
1$
#370
0(
0$
0#
0"
#375
0!
0)
1$
#380
1(
0$
1#
1"
#385
1!
1)
1$
#390
0!
0$
0"
#395
1$
#400
0$
0#
1"
#405
1$
#410
1!
0$
1#
#415
1$
#420
0!
0$
0#
#425
1$
#430
1!
0$
1#
#435
1$
#440
0(
0$
0#
0"
#445
0!
0)
1$
#450
0$
#455
1$
#460
1(
0$
1#
1"
#465
1!
1)
1$
#470
0(
0$
0#
0"
#475
0!
0)
1$
#480
1(
0$
1#
1"
#485
1!
1)
1$
#490
0$
#495
1$
#500
0!
0$
0#
#505
1$
#510
1!
0$
1#
#515
1$
#520
0!
0$
0#
#525
1$
#530
0(
1!
0$
0"
#535
0!
0)
1$
#540
0$
#545
1$
#550
0$
#555
1$
#560
1(
0$
1#
1"
#565
1!
1)
1$
#570
0$
#575
1$
#580
0!
0$
0#
#585
1$
#590
1!
0$
1#
#595
1$
#600
0(
0$
0#
0"
#605
0!
0)
1$
#610
1(
0$
1#
1"
#615
1!
1)
1$
#620
0!
0$
0"
#625
1$
#630
1!
0$
1"
#635
1$
#640
0!
0$
0#
#645
1$
#650
0(
1!
0$
0"
#655
0!
0)
1$
#660
1!
0$
1"
#665
1$
#670
0!
0$
0"
#675
1$
#680
1(
0$
1#
1"
#685
1!
1)
1$
#690
0(
0$
0#
0"
#695
0!
0)
1$
#700
1!
0$
1"
#705
1$
#710
0!
0$
0"
#715
1$
#720
1!
0$
1"
#725
1$
#730
0$
1#
0"
#735
1$
#740
0$
#745
1$
#750
1(
0!
0$
1"
#755
1!
1)
1$
#760
0$
#765
1$
#770
0(
0$
0#
0"
#775
0!
0)
1$
#780
1!
0$
1#
#785
1$
#790
0!
0$
0#
#795
1$
#800
1(
0$
1#
1"
#805
1!
1)
1$
#810
0(
0$
0#
0"
#815
0!
0)
1$
#820
1!
0$
1#
#825
1$
#830
0$
0#
1"
#835
1$
#840
0!
0$
0"
#845
1$
#850
1(
0$
1#
1"
#855
1!
1)
1$
#860
0(
0$
0#
0"
#865
0!
0)
1$
#870
1!
0$
1#
#875
1$
#880
0!
0$
0#
#885
1$
#890
1!
0$
1"
#895
1$
#900
0!
0$
0"
#905
1$
#910
1!
0$
1"
#915
1$
#920
1(
0!
0$
1#
#925
1!
1)
1$
#930
0(
0$
0#
0"
#935
0!
0)
1$
#940
0$
#945
1$
#950
1!
0$
1"
#955
1$
#960
0!
0$
0"
#965
1$
#970
1!
0$
1#
#975
1$
#980
1(
0!
0$
1"
#985
1!
1)
1$
#990
0!
0$
0"
#995
1$
#1000
1!
0$
1"
